coingecko_api/__init__.py
coingecko_api/cg_uteis.py
coingecko_api/coingecko_api.py
coingecko_api/excepcions.py
coingecko_api-1.2.dist-info/LICENSE
coingecko_api-1.2.dist-info/METADATA
coingecko_api-1.2.dist-info/WHEEL
coingecko_api-1.2.dist-info/top_level.txt
coingecko_api-1.2.dist-info/RECORD
